pylogger/__init__.py
pylogger/fnmatch2.py
pylogger/logger.py
pylogger-1.1.dist-info/entry_points.txt
pylogger-1.1.dist-info/top_level.txt
pylogger-1.1.dist-info/metadata.json
pylogger-1.1.dist-info/RECORD
pylogger-1.1.dist-info/METADATA
pylogger-1.1.dist-info/WHEEL
pylogger-1.1.dist-info/DESCRIPTION.rst
pylogger-1.1.dist-info/zip-safe
