Metadata-Version: 2.0
Name: pylogger
Version: 1.1
Summary: Send tailed logs to logstash with python
Home-page: https://github.com/BayanGroup/pylogger
Author: Bayan Group
Author-email: UNKNOWN
License: UNKNOWN
Keywords: logstash logger syslog tcp udp json
Platform: UNKNOWN
Classifier: Development Status :: 4 - Beta
Classifier: Intended Audience :: Developers
Classifier: License :: OSI Approved :: MIT License
Classifier: Operating System :: OS Independent
Classifier: Programming Language :: Python
Classifier: Programming Language :: Python :: 2
Classifier: Programming Language :: Python :: 3
Classifier: Topic :: Internet :: WWW/HTTP
Classifier: Topic :: Software Development :: Libraries :: Python Modules
Classifier: Topic :: System :: Logging
Requires-Dist: u-msgpack-python
Requires-Dist: tornado (>4)
Requires-Dist: PyYaml
Requires-Dist: jsonschema
